httpbin/__init__.py
httpbin/core.py
httpbin/filters.py
httpbin/helpers.py
httpbin/structures.py
httpbin/utils.py
httpbin/static/favicon.ico
httpbin/templates/UTF-8-demo.txt
httpbin/templates/footer.html
httpbin/templates/forms-post.html
httpbin/templates/httpbin.1.html
httpbin/templates/index.html
httpbin/templates/moby.html
httpbin/templates/sample.xml
httpbin/templates/trackingscripts.html
httpbin/templates/flasgger/index.html
httpbin/templates/images/jackal.jpg
httpbin/templates/images/pig_icon.png
httpbin/templates/images/svg_logo.svg
httpbin/templates/images/wolf_1.webp
httpbin-0.10.2.dist-info/AUTHORS
httpbin-0.10.2.dist-info/LICENSE
httpbin-0.10.2.dist-info/LICENSE.ISC
httpbin-0.10.2.dist-info/LICENSE.MIT
httpbin-0.10.2.dist-info/METADATA
httpbin-0.10.2.dist-info/WHEEL
httpbin-0.10.2.dist-info/top_level.txt
httpbin-0.10.2.dist-info/RECORD
