Metadata-Version: 2.1
Name: httpbin
Version: 0.10.2
Summary: HTTP Request and Response Service
Author-email: Kenneth Reitz <me@kennethreitz.org>
License: MIT or ISC
Project-URL: pypi, https://pypi.org/project/httpbin/
Project-URL: Repository, https://github.com/psf/httpbin
Classifier: Development Status :: 5 - Production/Stable
Classifier: Intended Audience :: Developers
Classifier: Natural Language :: English
Classifier: License :: OSI Approved :: ISC License (ISCL)
Classifier: License :: OSI Approved :: MIT License
Classifier: Programming Language :: Python
Classifier: Programming Language :: Python :: 3.7
Classifier: Programming Language :: Python :: 3.8
Classifier: Programming Language :: Python :: 3.9
Classifier: Programming Language :: Python :: 3.10
Classifier: Programming Language :: Python :: 3.11
Classifier: Programming Language :: Python :: 3.12
Requires-Python: >=3.7
License-File: LICENSE
License-File: LICENSE.ISC
License-File: LICENSE.MIT
License-File: AUTHORS
Requires-Dist: brotlicffi
Requires-Dist: decorator
Requires-Dist: flasgger
Requires-Dist: flask>=2.2.4
Requires-Dist: greenlet<3.0; python_version < "3.12"
Requires-Dist: greenlet>=3.0.0a1; python_version >= "3.12.0rc0"
Requires-Dist: importlib-metadata; python_version < "3.8"
Requires-Dist: six
Requires-Dist: werkzeug>=2.2.2
Provides-Extra: test
Requires-Dist: pytest; extra == "test"
Requires-Dist: tox; extra == "test"
Provides-Extra: mainapp
Requires-Dist: gunicorn; extra == "mainapp"
Requires-Dist: gevent; extra == "mainapp"
